{
  "id": "1089",
  "name": "花都汽車旅館",
  "area": "",
  "address": "南投縣集集鎮名水路二段380號",
  "phone": "049-276-3153",
  "fax": "049-276-3343",
  "website": "",
  "email": "flcity1014@yahoo.com.tw",
  "category": "汽車旅館",
  "stay_info": "平日進房時間：PM 12:00，退房時間：PM 12:00",
  "housing_rules": "休息時間：3小時\n住宿時間：平日進房時間：PM 12:00，退房時間：PM 12:00假日進房時間：PM 03:00，退房時間：PM 12:00住宿區分：平日週日至週五\n假日週六至週六如入住超過午夜12:00時則以12個小時為住宿時間\n\t\t\t\t\t\t\t\t\t\t\t\t\t\t\n\t\t\t\t\t\t\t\t\t\t\t\t\t\t\n\t\t\t\t\t\t\t\t\t\t\t\t\t\n\t\t\t\t\t\t\t\t\t\t\t\t\t\n\t\t\t\t\t\t\t\t\t\t\t\t\t\t\n\n\n\n\n(adsbygoogle = window.adsbygoogle || []).push({});",
  "precautions": "",
  "price_accommodation": null,
  "price_rest": null,
  "description": "本旅館有夜的寧靜,夢中的情懷帶給您無限的溫馨浪漫~且價格合理、服務親切，住宿休息皆宜,且交通方便,位於中二高下名間交流道,紅綠燈左轉,往集集方向,台16線7.5公里處即可到達,是您出發前往南投各風景名勝日月潭、九族文化村、水里.車程.風櫃斗.阿里山....等地的住宿最佳選擇本旅館備有按摩浴缸房.烤箱室房.蒸汽室房.商務房,房房彩繪,讓客人有更多享受的選擇。"
}
