{
  "id": "1364",
  "name": "龍昇商務休閒飯店",
  "area": "",
  "address": "台南市永康區中正南路123號",
  "phone": "06-282-3836",
  "fax": "06-282-3837",
  "website": "http://www.dragonhotel.com.tw",
  "email": "lonsan.hot@msa.hinet.net",
  "category": "飯店/旅館",
  "stay_info": "平日進房時間：PM 12:00，退房時間：PM 12:00",
  "housing_rules": "休息時間：3小時\n08:00~24:00 三小時,00:00~08:00 二小時\n住宿時間：平日進房時間：PM 12:00，退房時間：PM 12:00假日進房時間：PM 12:00，退房時間：PM 12:00住宿區分：平日週日至週四\n假日週五至週六00:00 ~08:00 住宿以12小時計\n\t\t\t\t\t\t\t\t\t\t\t\t\t\t\n\t\t\t\t\t\t\t\t\t\t\t\t\t\t\n\t\t\t\t\t\t\t\t\t\t\t\t\t\n\t\t\t\t\t\t\t\t\t\t\t\t\t\n\t\t\t\t\t\t\t\t\t\t\t\t\t\t\n\n\n\n\n(adsbygoogle = window.adsbygoogle || []).push({});",
  "precautions": "禁止攜帶違禁品\n禁止攜帶寵物",
  "price_accommodation": null,
  "price_rest": null,
  "description": "本飯店位於中山高速公路永康交流道台南縣市省道交界處約5分鐘車程,鄰近台南科學園區,科工區,市中心是您洽公考察~休閒旅遊~接待外賓最佳選擇.各式精緻套房,大型室內停車場,完善商務設施,豐富的休閒餐飲及體貼入微的服務,使您深刻感受:( 因為用心~倍感溫馨 )."
}
