{
  "id": "1430",
  "name": "打狗戀館",
  "area": "",
  "address": "高雄市小港區港平路167號",
  "phone": "07-812-9988",
  "fax": "07-812-0789",
  "website": "",
  "email": "takao.motel@msa.hinet.net",
  "category": "汽車旅館",
  "stay_info": "",
  "housing_rules": "(adsbygoogle = window.adsbygoogle || []).push({});",
  "precautions": "",
  "price_accommodation": null,
  "price_rest": null,
  "description": "35種愛戀  體驗35種愛情現場...\n\n在高雄國際機場旁\n我們起造了一座象徵純淨愛情的白色戀館\n精緻規劃了35種愛戀主題‥\n您可以在巧克力工場裡釀造甜蜜愛情\n或賴在呢絨羽被裡找尋鳥籠裡的春天\n\n想體驗不一樣的\n來個角色扮演重溫約會下課後的甜蜜\n沈浸在愛琴海的藍白裡當個被幸福圍繞的希臘新娘\n亦或體驗野性非洲的激情\n更可以在重現德川皇朝與摩洛哥天堂奢華浴場裡\n享受百坪皇族般的尊寵\n\n打狗戀館跨時空的多重主題風格與潔淨、安全、隱密設計\n滿足戀人們的所有需求\n讓您倆盡情體驗那屬於愛情的\n奢華狂野迷幻與溫柔的千變萬化‥"
}
