{
  "id": "2675",
  "name": "简体 手機版beta托斯卡尼",
  "area": "",
  "address": "屏東縣恆春鎮墾丁路石牛巷1-3號",
  "phone": "08-886-1283",
  "fax": "08-886-1275",
  "website": "http://tuscany.tw/",
  "email": "service@tuscany.tw",
  "category": "民宿",
  "stay_info": "",
  "rest_info": "",
  "housing_rules": "(adsbygoogle = window.adsbygoogle || []).push({});",
  "precautions": "",
  "description": "2003年一個平實的夜晚，不經意欣賞了一部改編自小說的電影 ─『托斯卡尼豔陽下』；在電影結束的片刻，細膩感受主角滿足而圓滿的心情，一幕幕既樸實又唯美的科托納小鎮，那一切自然到令人無法形容的美景，著實令人流連忘返；對於這份托斯卡尼帶給人的美好，當晚深深的留下印記。再回到墾丁這一片的土地時，帶著那一分悸動的心情，在這樣一個彷彿置身於托斯卡尼隱密的山城的環境裡，給了我相當的靈感，並且不斷的發酵著電影給人的感動，我希望能在這裡，一一將我受到的感受到的點滴心情分享給許多人，分享給許多願意為生活注入著許多細膩的情感，願意靜下心來享受這片靜溢的所有人，在這樣的環境裡產生共鳴。\n我們不斷的重看電影裡的每一個情節，每一個片段裡出現的個場景，托斯卡尼散發出的自然與樸實，真的無法取代；但漸漸的我們將其中的元素，一點一點的剝離，在一點一點的組合起來，對我而言這並不是僅止於一棟建築，反倒慢慢的變成是一種對生活的信仰，我深深的感受到劇中不斷在傳達的心情。終於在2007年的一月在墾丁的石牛溪農場中，我們完成了這棟托斯卡尼；如同劇中的主角在電影裡，將她的房子，修復完成的心情。在這一刻，我們也同時體驗到「當房子好了，一切就水到渠成了」…這份無法言喻的感動。",
  "images": [
    "https://www.qk.to/imgs/hotel_images/2675_l_image_72itz.jpg"
  ],
  "source_link": "https://www.qk.to/inquiry.asp?n=2675"
}