{
  "id": "2725",
  "name": "愛家精品旅館",
  "area": "",
  "address": "台中市梧棲區大仁路二段291巷10號",
  "phone": "04-2656-9668",
  "fax": "04-2656-9228",
  "website": "http://www.aplushotel.com.tw",
  "email": "aplushotel@gmail.com",
  "category": "飯店/旅館",
  "stay_info": "平日進房時間：PM 03:00，退房時間：PM 12:00",
  "housing_rules": "住宿時間：平日進房時間：PM 03:00，退房時間：PM 12:00假日進房時間：PM 03:00，退房時間：PM 12:00住宿區分：平日週日至週五\n假日週六至週六住宿時間超過凌晨3點，於下午3點退房\n\t\t\t\t\t\t\t\t\t\t\t\t\t\t\n\t\t\t\t\t\t\t\t\t\t\t\t\t\t\n\t\t\t\t\t\t\t\t\t\t\t\t\t\n\t\t\t\t\t\t\t\t\t\t\t\t\t\n\t\t\t\t\t\t\t\t\t\t\t\t\t\t\n\n\n\n\n(adsbygoogle = window.adsbygoogle || []).push({});",
  "precautions": "",
  "price_accommodation": null,
  "price_rest": null,
  "description": "現代紐約風的時尚精品旅館，摩登、簡約、自然，踏在木造地板的雙腳似乎也變得輕盈，享受生活，不需要太多理由，有事沒事我們在這裡等您，住上一晚。"
}
