{
  "id": "3208",
  "name": "简体 手機版beta台南維悅酒店",
  "area": "",
  "address": "台南市安平區慶平路539號",
  "phone": "06-295-0888",
  "fax": "06-295-0222",
  "website": "http://www.weiyat-hotel.com.tw/",
  "email": "",
  "category": "飯店/旅館",
  "stay_info": "",
  "rest_info": "",
  "housing_rules": "(adsbygoogle = window.adsbygoogle || []).push({});",
  "precautions": "",
  "description": "「維悅酒店」為台南著名景點-安平區內之地標酒店，位於安平運河畔，不僅可享受運河的美麗景色，並與安平眾多知名景點、伴手禮店家僅有一河之隔，是諸多旅客指名入住的飯店。\n此外，維悅酒店著重環境保護議題，提出環保住宿專案，獲頒【環保旅店】，共同為環境永續發展盡一份心力。",
  "images": null,
  "source_link": "https://www.qk.to/inquiry.asp?n=3208"
}