{
  "id": "3557",
  "name": "峻美精品旅店",
  "area": "",
  "address": "台北市中山區長春路62號6樓",
  "phone": "02-2531-2338",
  "fax": "02-2531-2337",
  "website": "http://www.beautyhotels.com.tw",
  "email": "bnight@beautyhotels.com.tw",
  "category": "飯店/旅館",
  "stay_info": "平日進房時間：PM 03:00，退房時間：PM 12:00",
  "housing_rules": "休息時間：平日2小時，假日2小時\n每加一小時300元\n住宿時間：平日進房時間：PM 03:00，退房時間：PM 12:00假日進房時間：PM 06:00，退房時間：PM 12:00住宿區分：平日週日至週四\n假日週五至週六凌晨24:00後入住為12小時\n\t\t\t\t\t\t\t\t\t\t\t\t\t\t\n\t\t\t\t\t\t\t\t\t\t\t\t\t\t\n\t\t\t\t\t\t\t\t\t\t\t\t\t\n\t\t\t\t\t\t\t\t\t\t\t\t\t\n\t\t\t\t\t\t\t\t\t\t\t\t\t\t\n\n\n\n\n(adsbygoogle = window.adsbygoogle || []).push({});",
  "precautions": "全館禁菸\n禁止攜帶寵物入內\n住宿以兩人為限。",
  "price_accommodation": null,
  "price_rest": null,
  "description": "峻美精品旅店 Hotel Bnight \n\n峻美精品旅店- 隸屬台北美系列飯店集團 旗下，峻美精品旅店 位於長春路，近林森北路口，座落於繁華熱鬧的中山區， 更毗鄰有台灣表參道之稱的中山北路時尚購物商圈， 除了時尚精品街，附近的南京商圈，有欣欣百貨、 新光三越1、2、3館，和到巷弄內的創意特色店面，甚至光點電影院、或是中山地下書街，從時尚與流行，到知性與悠閒，都會讓人發現無限驚喜。另外附近也有許多著名美食餐廳，像是日本料理的肥前屋、海之幸、小巷亭，或是上海點心的葡吉小廚，或是京星港式飲茶，或是乾杯、太田的日式燒烤，又或是雞家莊的台菜美味料理都可選擇﹔除了異國料理，週遭也有像高家莊米台苜等的平價美食，也能讓饕客趨之若鶩。\n\n峻美精品旅店 因位處地理位置相當優越的台北市中心，因此除了時尚文化、購物、娛樂外，步行間距離皆有便利商店、康是美、屈臣氏等美藥妝店、銀行、錢櫃KTV，晴光市場.等，食衣住行一應俱全。交通也位於樞紐，不僅附近有捷運中山站與捷運雙連站，也緊鄰台北地區各公車銜接處，讓您能輕鬆到達台北車站、高鐵台北站等交通要站，也能方便到訪台北其他著名景點，如士林夜市、台北故事館、國立故宮博物院、北投溫泉、淡水老街等，讓您不管是洽公，或是旅行，都能讓您的行程帶來更多便利。\n\n峻美精品旅店 將讓您感受 台北美系列飯店集團 所帶給您的另一個不同體驗，也必成為您住宿的優質之選。"
}
