{
  "id": "751",
  "name": "雲景溫泉渡假山莊",
  "area": "",
  "address": "新北市烏來區西羅岸路81號",
  "phone": "02-2661-6695",
  "fax": "//\u003c![CDATA[\n  var tlJsHost = ((window.location.protocol == \"https:\") ? \"https://secure.trust-provider.com/\" : \"http://www.trustlogo.com/\");\n  document.write(unescape(\"%3Cscript src='\" + tlJsHost + \"trustlogo/javascript/trustlogo.js' type='text/javascript'%3E%3C/script%3E\"));\n//]]\u003e\n\n  TrustLogo(\"https://ssl.comodo.com/images/seals/sectigo_trust_seal_sm_2x.png\", \"SECDV\", \"none\");\n\n\t\t\t\t\t\t\t\t\t\t\n\t\t\t\t\n\t\t\t\tQK休閒網 版權所有  Copyright © 2004 QK Network Leisure All Rights Reserved傳真：04-735-8949    EMail：Service@Qk.to   隱私權   粉絲團   聯絡我們",
  "website": "",
  "email": "enjoy@itrust.to",
  "category": "溫泉泡湯",
  "stay_info": "",
  "housing_rules": "(adsbygoogle = window.adsbygoogle || []).push({});",
  "precautions": "雲景山莊現只有11間客房可供住宿，但間間別緻，各有特色，除了設計精雅外，更可一覽烏來山水無遺，可說「天下好湯在烏來，烏來好景在雲景」。民生報更有質佳景美之譽。內有湯屋、檜木桶、SPA設備，也提供芳香按摩服務。房間更是寬敞舒適，傢俱裝潢更是精挑細選，樣樣用心，彷彿置身於歐洲宮廷，尊寵又自如。比起國外頂級的度假村，一點也不遜色。\n備註：\n1．用餐及小孩使用大眾湯，每位半價優惠。\n2．住宿平日(週日至週五)六折，假日(週六、國定假日前夕及連續假期)八折優惠並附贈早餐及免費露天SPA。\n3．以上房型除有標示外一律以兩人為主。\n4．10歲以上小孩加收兒童價格。\n5．泡湯平日(週一至週五)1.5小時，假日(週六、國定假日前夕及連續假期)1小時。\n6．標準客房住宿平日1990元，假日2990元(含早餐)。",
  "price_accommodation": null,
  "price_rest": null,
  "description": ""
}
